{
  "company": {
    "name": "РемонтМастер",
    "phone": "+7 (999) 009898988",
    "city": "Москва"
  },
  "stats": [
    {
      "num": "150+",
      "label": "сданных объектов"
    },
    {
      "num": "10 лет",
      "label": "на рынке"
    },
    {
      "num": "2 года",
      "label": "гарантия"
    },
    {
      "num": "0 ₽",
      "label": "скрытых доплат"
    }
  ],
  "roomTypes": [
    {
      "label": "Обои, покраска, полы",
      "pricePerSqm": 3500
    },
    {
      "label": "Замена труб, проводки, полов",
      "pricePerSqm": 6500
    },
    {
      "label": "Евроремонт под ключ",
      "pricePerSqm": 10000
    },
    {
      "label": "Дизайнерский",
      "pricePerSqm": 16000
    }
  ],
  "portfolio": [
    {
      "title": "3-комнатная квартира, Кутузовский",
      "area": "89 м²",
      "type": "Евроремонт",
      "days": "47 дней",
      "before": "https://images.unsplash.com/photo-1484154218962-a197022b5858?w=600&q=80",
      "after": "https://images.unsplash.com/photo-1600210492493-0946911123ea?w=600&q=80"
    },
    {
      "title": "Студия, Новая Москва",
      "area": "42 м²",
      "type": "Под ключ",
      "days": "28 дней",
      "before": "https://images.unsplash.com/photo-1558618666-fcd25c85cd64?w=600&q=80",
      "after": "https://images.unsplash.com/photo-1600585154340-be6161a56a0c?w=600&q=80"
    },
    {
      "title": "2-комнатная, Пресня",
      "area": "65 м²",
      "type": "Дизайнерский",
      "days": "61 день",
      "before": "https://images.unsplash.com/photo-1512917774080-9991f1c4c750?w=600&q=80",
      "after": "https://images.unsplash.com/photo-1600566752355-35792bedcfea?w=600&q=80"
    }
  ],
  "steps": [
    { "step": "01", "title": "Бесплатный замер", "desc": "Выезжаем в удобное время, замеряем и составляем детальную смету — без скрытых позиций" },
    { "step": "02", "title": "Договор с фиксированной ценой", "desc": "Прописываем цену, сроки и штрафы за просрочку. Платите поэтапно — 30/40/30%" },
    { "step": "03", "title": "Ремонт с фотоотчётами", "desc": "Работаем по технологии, убираем мусор ежедневно. Фото в WhatsApp каждый день" },
    { "step": "04", "title": "Сдача и гарантия", "desc": "Принимаете работу по акту. Гарантия 2 года — если что-то не так, приедем и исправим" }
  ],
  "faq": [
    { "q": "Почему цена фиксированная? Это реально?", "a": "Да. Мы делаем детальный замер и прописываем все работы в смете до копейки. Если что-то упустили при замере — это наша ошибка, клиент не доплачивает." },
    { "q": "Что если вы не уложитесь в срок?", "a": "В договоре прописана неустойка — 0,5% от суммы за каждый день просрочки. Это дисциплинирует лучше любых обещаний." },
    { "q": "Можно ли купить материалы самому?", "a": "Да. Вы можете купить материалы сами — тогда мы работаем только за услуги. Или доверить закупку нам — у нас есть скидки у поставщиков до 15%." },
    { "q": "Как проходит оплата?", "a": "Поэтапно: 30% аванс, 40% после черновых работ, 30% при сдаче объекта. Никаких полных предоплат." },
    { "q": "Какая гарантия на работы?", "a": "2 года на все виды работ. Если что-то отвалится — приедем и переделаем бесплатно." }
  ],
  "reviews": [
    {
      "name": "Анна Петрова",
      "city": "Москва, Хамовники",
      "text": "Делали евроремонт в двушке. Всё строго по смете — ни рубля сверху. Закончили на 3 дня раньше срока. Особенно понравились ежедневные фото в WhatsApp — было спокойно.",
      "rating": 5,
      "project": "Евроремонт, 58 м²"
    },
    {
      "name": "Дмитрий Козлов",
      "city": "Москва, Митино",
      "text": "Скептически относился к фиксированной цене — думал, найдут повод доплатить. Но нет — всё как в договоре. Бригада аккуратная, мусор убирали каждый день.",
      "rating": 5,
      "project": "Капитальный ремонт, 74 м²"
    },
    {
      "name": "Светлана Морозова",
      "city": "Москва, Бутово",
      "text": "Обращалась уже второй раз — сначала делали коридор и кухню, теперь всю квартиру. Качество стабильное, мастера вежливые. Рекомендую без оговорок.",
      "rating": 5,
      "project": "Под ключ, 91 м²"
    }
  ]
}